{"cameraMode":{"drawMode":0,"name":"Shaded","section":"Shading Mode"},"sceneLighting":true,"audioPlay":false,"sceneViewState":{"m_AlwaysRefresh":false,"showFog":true,"showSkybox":true,"showFlares":true,"showImageEffects":true,"showParticleSystems":true,"showVisualEffectGraphs":true,"m_FxEnabled":true},"in2DMode":false,"pivot":{"x":4.05873966217041,"y":6.26479434967041,"z":2.2067153453826906},"rotation":{"x":-0.016166791319847108,"y":0.9833852052688599,"z":-0.1413964033126831,"w":-0.11229154467582703},"size":1.8331373929977418,"orthographic":false}